{"digest":"5f6325bfbaf065beb4d5cdbd37c1969f008e4e6c","css":".theme-atom-light-ui .tool-bar button.tool-bar-btn {\n  background-image: -webkit-linear-gradient(#f4f4f4, #e0e0e0);\n}\n.theme-atom-light-ui .tool-bar button.tool-bar-btn:hover {\n  background-image: -webkit-linear-gradient(#ffffff, #ebebeb);\n}\n.theme-atom-light-ui .tool-bar-top {\n  border-left: 0 none;\n  border-top: 0 none;\n  border-right: 0 none;\n}\n.theme-atom-light-ui .tool-bar-right {\n  border: 0 none;\n}\n.theme-atom-light-ui .tool-bar-bottom {\n  border: 0 none;\n}\n.theme-atom-light-ui .tool-bar-left {\n  border: 0 none;\n}\n","imports":[{"path":"static/variables/ui-variables.less","digest":"e3029f763111ec391f6dcea8178d35be7c798b4f"},{"path":"static/variables/syntax-variables.less","digest":"812c1b7883a023f768773d14294653adcdb932d7"}],"version":1}